django_stacktrace/__init__.py
django_stacktrace/admin.py
django_stacktrace/apps.py
django_stacktrace/event_builder/__init__.py
django_stacktrace/event_builder/builder.py
django_stacktrace/event_builder/contexts.py
django_stacktrace/event_builder/exception.py
django_stacktrace/event_builder/request.py
django_stacktrace/event_builder/serialization.py
django_stacktrace/event_builder/types.py
django_stacktrace/event_builder/user.py
django_stacktrace/event_store/__init__.py
django_stacktrace/event_store/model_data.py
django_stacktrace/event_store/sampling.py
django_stacktrace/event_store/store.py
django_stacktrace/middleware.py
django_stacktrace/migrations/0001_initial.py
django_stacktrace/migrations/__init__.py
django_stacktrace/models.py
django_stacktrace/py.typed
django_stacktrace/settings.py
django_stacktrace/signals.py
django_stacktrace/templates/admin/django_stacktrace/crashevent/change_list.html
django_stacktrace/tests/README.md
django_stacktrace/tests/__init__.py
django_stacktrace/tests/settings.py
django_stacktrace/tests/test_event_builder.py
django_stacktrace/tests/test_event_store.py
django_stacktrace/tests/urls.py
django_stacktrace-0.2.3.dist-info/WHEEL
django_stacktrace-0.2.3.dist-info/METADATA
django_stacktrace-0.2.3.dist-info/RECORD
