Metadata-Version: 2.3
Name: django-stacktrace
Version: 0.2.3
Summary: A reusable Django app that captures exceptions with request context and stores them in the database, similar to a lightweight Sentry
Author: Marsel Beqiri
Author-email: Marsel Beqiri <marselbeqiri.365@gmail.com>
License: MIT
Classifier: Development Status :: 4 - Beta
Classifier: Environment :: Web Environment
Classifier: Framework :: Django
Classifier: Framework :: Django :: 4.2
Classifier: Framework :: Django :: 5.0
Classifier: Intended Audience :: Developers
Classifier: License :: OSI Approved :: MIT License
Classifier: Operating System :: OS Independent
Classifier: Programming Language :: Python
Classifier: Programming Language :: Python :: 3
Classifier: Programming Language :: Python :: 3.12
Classifier: Topic :: Internet :: WWW/HTTP
Classifier: Topic :: Internet :: WWW/HTTP :: Dynamic Content
Classifier: Topic :: Software Development :: Libraries :: Python Modules
Classifier: Topic :: System :: Logging
Requires-Dist: django>=4.2
Requires-Python: >=3.12
Project-URL: Homepage, https://github.com/marselbeqiri/django-stacktrace
Project-URL: Documentation, https://github.com/marselbeqiri/django-stacktrace#readme
Project-URL: Source, https://github.com/marselbeqiri/django-stacktrace
Project-URL: Tracker, https://github.com/marselbeqiri/django-stacktrace/issues
Project-URL: Release notes, https://github.com/marselbeqiri/django-stacktrace/releases
